SuperClaude/__init__.py
SuperClaude/__main__.py
SuperClaude/Commands/__init__.py
SuperClaude/Commands/analyze.md
SuperClaude/Commands/build.md
SuperClaude/Commands/cleanup.md
SuperClaude/Commands/design.md
SuperClaude/Commands/document.md
SuperClaude/Commands/estimate.md
SuperClaude/Commands/explain.md
SuperClaude/Commands/git.md
SuperClaude/Commands/implement.md
SuperClaude/Commands/improve.md
SuperClaude/Commands/index.md
SuperClaude/Commands/load.md
SuperClaude/Commands/spawn.md
SuperClaude/Commands/task.md
SuperClaude/Commands/test.md
SuperClaude/Commands/troubleshoot.md
SuperClaude/Commands/workflow.md
SuperClaude/Core/CLAUDE.md
SuperClaude/Core/COMMANDS.md
SuperClaude/Core/FLAGS.md
SuperClaude/Core/GEMINI.md
SuperClaude/Core/MCP.md
SuperClaude/Core/MODES.md
SuperClaude/Core/ORCHESTRATOR.md
SuperClaude/Core/PERSONAS.md
SuperClaude/Core/PRINCIPLES.md
SuperClaude/Core/RULES.md
SuperClaude/Core/__init__.py
SuperClaude/GeminiCommands/__init__.py
SuperClaude/GeminiCommands/analyze.md
SuperClaude/GeminiCommands/build.md
SuperClaude/GeminiCommands/cleanup.md
SuperClaude/GeminiCommands/design.md
SuperClaude/GeminiCommands/document.md
SuperClaude/GeminiCommands/estimate.md
SuperClaude/GeminiCommands/explain.md
SuperClaude/GeminiCommands/git.md
SuperClaude/GeminiCommands/implement.md
SuperClaude/GeminiCommands/improve.md
SuperClaude/GeminiCommands/index.md
SuperClaude/GeminiCommands/load.md
SuperClaude/GeminiCommands/spawn.md
SuperClaude/GeminiCommands/task.md
SuperClaude/GeminiCommands/test.md
SuperClaude/GeminiCommands/troubleshoot.md
SuperClaude/GeminiCommands/workflow.md
SuperClaude/GeminiCore/COMMANDS.md
SuperClaude/GeminiCore/FLAGS.md
SuperClaude/GeminiCore/GEMINI.md
SuperClaude/GeminiCore/MCP.md
SuperClaude/GeminiCore/MODES.md
SuperClaude/GeminiCore/ORCHESTRATOR.md
SuperClaude/GeminiCore/PERSONAS.md
SuperClaude/GeminiCore/PRINCIPLES.md
SuperClaude/GeminiCore/RULES.md
SuperClaude/GeminiCore/__init__.py
SuperClaude/Hooks/PLACEHOLDER.py
SuperClaude/Hooks/__init__.py
superclaude_gemini_fetch-3.0.0.dist-info/METADATA
superclaude_gemini_fetch-3.0.0.dist-info/WHEEL
superclaude_gemini_fetch-3.0.0.dist-info/entry_points.txt
superclaude_gemini_fetch-3.0.0.dist-info/licenses/LICENSE
superclaude_gemini_fetch-3.0.0.dist-info/RECORD
