Metadata-Version: 2.4
Name: SuperClaude-gemini-fetch
Version: 3.0.0
Summary: A Gemini-focused version of the SuperClaude framework
Project-URL: Homepage, https://github.com/SuperClaude-Org/SuperClaude_Framework
Project-URL: Repository, https://github.com/SuperClaude-Org/SuperClaude_Framework
Project-URL: Bug Tracker, https://github.com/SuperClaude-Org/SuperClaude_Framework/issues
Project-URL: GitHub, https://github.com/SuperClaude-Org/SuperClaude_Framework
Project-URL: Mithun Gowda B, https://github.com/mithun50
Project-URL: NomenAK, https://github.com/NomenAK
Author-email: Mithun Gowda B <contact@superclaude.dev>, NomenAK <contact@superclaude.dev>
License: MIT
License-File: LICENSE
Classifier: Development Status :: 4 - Beta
Classifier: Intended Audience :: Developers
Classifier: License :: OSI Approved :: MIT License
Classifier: Operating System :: OS Independent
Classifier: Programming Language :: Python :: 3
Classifier: Programming Language :: Python :: 3.8
Classifier: Programming Language :: Python :: 3.9
Classifier: Programming Language :: Python :: 3.10
Classifier: Programming Language :: Python :: 3.11
Classifier: Programming Language :: Python :: 3.12
Requires-Python: >=3.8
Requires-Dist: setuptools>=45.0.0
